memory_utils/__init__.py
memory_utils-1.0.2.dist-info/DESCRIPTION.rst
memory_utils-1.0.2.dist-info/LICENSE.txt
memory_utils-1.0.2.dist-info/METADATA
memory_utils-1.0.2.dist-info/RECORD
memory_utils-1.0.2.dist-info/WHEEL
memory_utils-1.0.2.dist-info/metadata.json
memory_utils-1.0.2.dist-info/top_level.txt
