Metadata-Version: 2.0
Name: memory-utils
Version: 1.0.2
Summary: Tools to help with memory leaks
Home-page: http://github.com/jtushman/memory_utils
Author: Jonathan Tushman
Author-email: jonathan@zefr.com
License: MIT
Platform: UNKNOWN
Classifier: Intended Audience :: Developers
Classifier: License :: OSI Approved :: MIT License
Classifier: Programming Language :: Python :: 2.7
Classifier: Programming Language :: Python :: 3.4
Classifier: Programming Language :: Python :: 3.5
Classifier: Programming Language :: Python :: 3.6
Requires-Dist: colorama (>=0.3.2)
Requires-Dist: psutil (>=2.1.1)
Requires-Dist: six
